{
 "DGX": {
  "detail": "> **今日漲因:** 盤前 +7.7% — Quest Diagnostics 7/23 盤前公布 Q2 財報,調整後 EPS **$3.12** 超預期 **$2.82**(+10.6%)、營收 **$30.4億(+10.2% YoY)**,並**上調全年財測**。\n\n診斷檢測量年增 **12%**,帶動營收超標;GAAP 每股盈餘 $2.84(+15% YoY),營業利益率 15.1%。\n\n公司同步**調高全年指引**:調整後 EPS 由 $10.63-10.83 上修至 **$11.05-11.25**,營收上修至 **$11.95-12.05億**。屬乾淨的品質型財報跳空,大型醫療診斷龍頭。\n\n客觀提醒:過去 5 年在營收持平下 EPS 年均下滑約 7.5%,全年營收成長預估約 4.5%(較前兩年放緩),留意利潤率壓力。",
  "publishedAt": "2026-07-23T06:30:00-04:00",
  "publishedTimezone": "ET",
  "sources": [
   { "label": "Quest Diagnostics Q2 2026 新聞稿 (PR Newswire)", "url": "https://www.prnewswire.com/news-releases/quest-diagnostics-reports-second-quarter-2026-financial-results-raises-revenue-and-eps-guidance-for-full-year-2026-302832675.html" },
   { "label": "RTTNews — DGX 上調 FY26 展望", "url": "https://www.rttnews.com/3669922/quest-diagnostics-boosts-fy26-outlook-shares-up-5-7-update.aspx" }
  ]
 },
 "RTX": {
  "detail": "> **今日漲因:** +5.2% — RTX Q2 財報全面超預期並**上調全年獲利指引**,調整後 EPS **$1.89** 勝預期 **$1.66**、營收 **$247.1億(+14.5% YoY)** 超標近 8%。\n\n成長由 Pratt & Whitney 引擎、Collins Aerospace 航電與 Raytheon 國防三引擎同步驅動;營業利益率由去年 9.9% 升至 **11.4%**,自由現金流 **$28.8億**(去年為 -$0.72億)。\n\n公司**上修全年財測**:營收中值調至 **$955億**、調整後 EPS 中值調至 **$7.18**。國防+航太雙引擎、積壓訂單強,屬品質型財報 SIP。",
  "publishedAt": "2026-07-22T06:30:00-04:00",
  "publishedTimezone": "ET",
  "sources": [
   { "label": "Seeking Alpha — RTX 上調展望", "url": "https://seekingalpha.com/news/4617269-rtx-raises-outlook-after-earnings-top-estimates-on-aerospace-defense-demand" }
  ]
 },
 "NOW": {
  "detail": "> **今日漲因:** +5% — ServiceNow 7/22 盤後公布 Q2,訂閱營收 **$38.77億(+24.5% YoY)** 超預期,AI 年度合約額(ACV)突破 **$10億**,並**上調全年指引**,緩解市場對 AI 變現的疑慮。\n\n淨新增 ACV 環比加速逾 40%,單季逾 **123 筆 >$100萬** 的大單(+40% YoY),續約率 **98%**;非 GAAP 每股盈餘 $0.90。\n\n公司**上修全年**:訂閱營收至 **$157.6-157.8億**、非 GAAP 營業利益率至 31.5%,並將 AI ACV 目標由 >$10億 上調至 **2026 年底 $15億**。結構性 AI 軟體成長股。\n\n客觀提醒:管理層示警 Q3 有約 $3500萬 匯率逆風。",
  "publishedAt": "2026-07-22T16:05:00-04:00",
  "publishedTimezone": "ET",
  "sources": [
   { "label": "ServiceNow Q2 2026 新聞稿", "url": "https://newsroom.servicenow.com/press-releases/details/2026/ServiceNow-Reports-Second-Quarter-2026-Financial-Results/default.aspx" },
   { "label": "Seeking Alpha — NOW 上調訂閱與 AI ACV 目標", "url": "https://seekingalpha.com/news/4617135-servicenow-signals-2026-subscription-revenue-of-15_770b-while-targeting-1_5b-ai-acv-by-end-of" }
  ]
 },
 "ALLE": {
  "detail": "> **今日漲因:** 盤前 +10% — Allegion(門禁安控)Q2 EPS **$2.40** 超預期 **$2.22**(+8.3%)、營收 **$11.5億(+12.7% YoY)**,並**上調全年展望**,是今日最強的乾淨大型股財報跳空。\n\n有機成長 +6.9%;調整後 EBITDA **$2.967億**(超估近 8%),EBITDA 利潤率 25.8%,營業利益率 22.1%。\n\n公司**上修全年**調整後 EPS 中值至 **$8.93**,隱含約 9.3% 的 EPS 成長。beat-and-raise 的教科書式財報。",
  "publishedAt": "2026-07-23T06:18:00-04:00",
  "publishedTimezone": "ET",
  "sources": [
   { "label": "Allegion Q2 2026 8-K 新聞稿 (SEC)", "url": "https://www.sec.gov/Archives/edgar/data/0001579241/000157924126000013/exhibit991-pressreleasedat.htm" }
  ]
 },
 "ACI": {
  "detail": "> **今日跌因:** 盤前重挫 -18.5% — Albertsons Q1 調整後 EPS **$0.42 遜於預期 $0.54**,更**大砍全年財測**:調整後 EPS 由市場預期 $2.27 下修至 **$1.75-1.85**、調整後 EBITDA 由 $38.5億 下修至 **$35.5-36.25億**。\n\n同店銷售 -0.8%,數位銷售 +13% 但毛利率受配送/處理與燃油成本上升侵蝕;藥局銷售雖成長仍受 IRA 政策壓力。\n\n風險面:與 Kroger 併購破局後的德拉瓦衡平法院訴訟仍進行中;股利發放率已逾 100%,永續性受質疑;槓桿偏高。基本面明確轉弱,方向做空。\n\n**軋空提醒:** Short Float **15.3%**、回補天數 **7.35 天**,做空需嚴設停損防軋空。",
  "publishedAt": "2026-07-23T07:00:00-04:00",
  "publishedTimezone": "ET",
  "sources": [
   { "label": "Yahoo Finance — Albertsons 砍財測重挫", "url": "https://finance.yahoo.com/markets/stocks/articles/albertsons-tumbles-earnings-miss-slashed-121750413.html" },
   { "label": "Seeking Alpha — ACI 下修指引", "url": "https://seekingalpha.com/news/4617244-albertsons-plunges-after-slashing-guidance-kroger-also-lower" }
  ]
 },
 "WST": {
  "detail": "> **今日漲因:** 盤前 +6% — West Pharmaceutical(注射藥包材/給藥裝置)Q2 營收 **$8.72億(+13.8% YoY)** 超預期、調整後 EPS **$2.37** 勝預期 **$2.08**(+13.9%),並**上調全年財測**。\n\nEPS 較去年同期 +28.8%;公司**上修全年**營收至中值 **$33.6億**、調整後 EPS 至中值 **$8.95**。醫材耗材需求回溫。\n\n客觀提醒:過去 5 年調整後營業利益率下滑約 5.5 個百分點,未來 12 個月營收成長預估僅約 1.3%(較前兩年放緩)。",
  "publishedAt": "2026-07-23T06:30:00-04:00",
  "publishedTimezone": "ET",
  "sources": [
   { "label": "West Pharmaceutical Q2 2026 8-K (SEC)", "url": "https://www.sec.gov/Archives/edgar/data/0000105770/000010577026000047/exh991q12026earningsrelease.htm" }
  ]
 },
 "STM": {
  "detail": "> **今日跌因:** 盤前重挫逾 -15% — STMicroelectronics Q2 營收 **$34.9億(+26% YoY)** 雖優於展望中值,但市場聚焦於**可轉債稀釋**與利潤率壓力。\n\n非 GAAP 每股盈餘約 $0.31、毛利率 34.8%(含未用產能費用),Q3 展望營收 $37億、毛利率約 37%;資料中心營收展望上調至 2026 年 **>$10億**、2027 年上看 >$20億(矽光子/800G-1.6T 光通訊)。\n\n**主要利空:** 公司定價 **$15億** 雙檔(5 年/7 年各 $7.5億)無擔保可轉債,部分用於贖回 2027 年到期的 $7.5億 零息可轉債,引發稀釋與套利/放空;股價前 30 日已跌逾 20%。方向做空,惟需留意基本面其實穩健、可能出現反彈。",
  "publishedAt": "2026-07-23T02:00:00-04:00",
  "publishedTimezone": "ET",
  "sources": [
   { "label": "STMicroelectronics Q2 2026 新聞稿 (GlobeNewswire)", "url": "https://www.globenewswire.com/news-release/2026/07/23/3331866/0/en/STMicroelectronics-Reports-Q2-2026-Financial-Results.html" },
   { "label": "Ad-hoc News — STM $15億可轉債定價", "url": "https://www.ad-hoc-news.de/boerse/news/ueberblick/stmicroelectronics-stock-1-5-billion-convertible-bond-offering-prices/69565028" }
  ]
 },
 "TSLA": {
  "detail": "> **今日跌因:** 盤後/盤前跌約 -7% — Tesla Q2 營收 **$282.4億(+26% YoY)** 優於預期、交車 **480,126 輛**(超估約 18%),但**獲利品質大幅惡化**:調整後 EPS **$0.33 遠低於預期**、GAAP 營業利益年減 **57%** 至 $3.98億。\n\n營業利益率由去年 4.1% 壓縮至僅 **1.4%**;營業費用 +47% 至 $43.5億(AI/研發投入),毛利率因平均售價下滑與監管積分收入減少而不如預期;淨利年減 5% 至 $11.1億(部分靠投資收益撐)。\n\n市場懲罰的是「營收成長但利潤與自由現金流惡化」。方向偏空。",
  "publishedAt": "2026-07-22T16:05:00-04:00",
  "publishedTimezone": "ET",
  "sources": [
   { "label": "CNBC — Tesla Q2 2026 財報", "url": "https://www.cnbc.com/2026/07/22/tesla-tsla-q2-2026-earnings-report.html" },
   { "label": "Electrek — Tesla Q2 2026 財務結果", "url": "https://electrek.co/2026/07/22/tesla-tsla-q2-2026-financial-results/" }
  ]
 },
 "DOMO": {
  "detail": "> **今日漲因:** 盤前暴漲逾 +34% — Domo 宣布將**幾乎全部資產與營運業務出售予 Progress Software,現金對價約 $4億**(7/22 公布)。\n\n收購涵蓋 Domo 的 AI/數據平台、技術、2,400+ 家客戶合約、員工與智慧財產;預計在 Progress 2026 財年(截至 11/30)前完成,尚待監管核准。\n\n交易後 Domo 保留約 **$2.46億** 淨現金(約每股 $4.84),對價較 30 日成交量加權均價溢價 **81%**;已取得主要股東投票支持協議。\n\n客觀提醒:交易尚未完成,仍受成交條件/監管審查影響;且股價一個月內已漲約 87%,追高風險高、宜快進快出。",
  "publishedAt": "2026-07-22T16:30:00-04:00",
  "publishedTimezone": "ET",
  "sources": [
   { "label": "Domo 新聞稿 — 出售資產予 Progress $4億", "url": "https://www.domo.com/news/press/domo-announces-agreement-to-sell-substantially-all-assets-and-certain-liabilities-to-progress-software-for-400-million" },
   { "label": "StockTitan — Progress 收購 Domo AI/數據平台", "url": "https://www.stocktitan.net/news/PRGS/progress-software-to-acquire-domo-s-ai-and-data-platform-nwg9nukydxq2.html" }
  ]
 },
 "RELL": {
  "detail": "> **今日漲因:** +17.6% — Richardson Electronics(RELL)Q4 FY2026 營收 **$6620萬(+27.6% YoY)** 大超預期(勝約 $970萬)、非 GAAP EPS **$0.21** 遠勝預期 **$0.07**,積壓訂單創 3 年新高。\n\n三大部門齊揚:功率與微波(PMT)$4,750萬(+28.1%)、綠能(GES)$650萬(+20.4%)、Canvys $1,230萬(+29.5%);積壓訂單 **$1.644億**(3 年高)。全年營收 $2.286億(+9.4%),GAAP EPS 由去年虧 $0.08 轉為 **$0.44**。\n\n同步宣布每股 $0.06 季度股利(8/7 登記、8/26 發放)。\n\n客觀提醒:Q4 含一次性 $80萬 醫療資產處分利益與 $40萬 州政府無主財產和解費;小型股、流通小、波動大。",
  "publishedAt": "2026-07-22T16:05:00-04:00",
  "publishedTimezone": "ET",
  "sources": [
   { "label": "Richardson Electronics Q4 FY2026 新聞稿 (GlobeNewswire)", "url": "https://www.globenewswire.com/news-release/2026/07/22/3331744/0/en/Richardson-Electronics-Reports-Strong-Fourth-Quarter-and-Fiscal-2026-Results-Declares-Quarterly-Cash-Dividend.html" }
  ]
 },
 "LMT": {
  "detail": "> **今日漲因:** +5% — Lockheed Martin Q2 調整後 EPS **$7.94** 勝預期 **$7.22**、營收 **$201億(+10.5% YoY)** 超標,並**上調全年展望**,積壓訂單創紀錄 **$2,300億**。\n\n單季新增訂單 $650億;飛彈與火控部門營收/營業利益各 +8%(PAC-3、JASSM、PrSM 需求)。惟航太部門利益 -14%(F-16 不利調整 $1.25億 + C-130J 沖銷 $5,500萬)。\n\n公司**上修全年**:EPS 至 **$29.95-30.65**、營收至 **$797.5-817.5億**,自由現金流 >$70億。國防龍頭品質財報。",
  "publishedAt": "2026-07-22T07:00:00-04:00",
  "publishedTimezone": "ET",
  "sources": [
   { "label": "Lockheed Martin Q2 2026 財報 (IR)", "url": "https://investors.lockheedmartin.com/news-releases/news-release-details/lockheed-martin-reports-second-quarter-2026-financial-results/" }
  ]
 },
 "ROP": {
  "detail": "> **今日漲因:** +5.5% — Roper Technologies Q2 營收 **$21億(+9% YoY)**,並**上調全年獲利財測**,受惠 AI 軟體需求橫跨醫療、運輸、教育垂直領域。\n\nCEO Neil Hunn 提及「擴大的 AI 產能與加速的執行速度」帶動軟體銷售;自由現金流 +11%。\n\n公司**上修全年**調整後每股盈餘至 **$21.80-22.05**,並上調營收成長財測。\n\n(註:部分來源對 Q2 實際 EPS 數字有出入,以公司上調財測與 AI 軟體動能為主軸。)",
  "publishedAt": "2026-07-21T07:00:00-04:00",
  "publishedTimezone": "ET",
  "sources": [
   { "label": "Reuters/Streetinsider — Roper 上調 2026 獲利財測", "url": "https://www.streetinsider.com/Reuters/Roper+Technologies+raises+2026+profit+forecast+as+AI+demand+boosts+software+sales/26355259.html" }
  ]
 },
 "CX": {
  "detail": "> **今日漲因:** 盤前 +6% — Cemex Q2 EBITDA 創紀錄 **$10億(+24% YoY)**、EBITDA 利潤率 +2.1 個百分點至 22.2%,並**上調全年 EBITDA 財測**。\n\n營業利益 +38%,營運自由現金流年增三倍至 **$6.37億**;「Project Cutting Edge」成本節約目標上調 $7,500萬 至 **$4.75億**。\n\n公司**上修全年 EBITDA 成長財測**由原本高個位數上調至 **16-17%**。營運效率明顯改善。",
  "publishedAt": "2026-07-23T07:02:00-04:00",
  "publishedTimezone": "ET",
  "sources": [
   { "label": "Cemex Q2 2026 6-K 財報 (SEC)", "url": "https://www.sec.gov/Archives/edgar/data/0001076378/000119312526313194/d46310dex1.htm" }
  ]
 },
 "ROL": {
  "detail": "> **今日跌因:** 盤後重挫約 -14% 至 -17% — Rollins(害蟲防治)Q2 營收 **$10.79億(+7.9% YoY)遜於預期 $11.03億**、調整後 EPS **$0.32 遜於預期 $0.344**,雖為連續第 99 季營收成長,仍不敵市場高標。\n\n住宅害蟲防治需求(消費端驅動)轉弱,壓抑利潤率;成本結構是為更強的成長而建,實際成長未達預期。\n\n方向偏空,惟屬防禦型穩健成長股,跌幅可能過度反應。",
  "publishedAt": "2026-07-22T16:15:00-04:00",
  "publishedTimezone": "ET",
  "sources": [
   { "label": "Rollins Q2 2026 8-K (SEC)", "url": "https://www.sec.gov/Archives/edgar/data/0000084839/000008483926000038/rol-20260722xex991.htm" }
  ]
 }
}
