{
  "PSTV": {
    "date": "2026-06-24",
    "open": 4.07,
    "high": 4.18,
    "low": 3.9,
    "close": 3.96,
    "volume": 95500,
    "prev_close": 4.08
  },
  "POET": {
    "date": "2026-06-24",
    "open": 10.81,
    "high": 11.65,
    "low": 10.35,
    "close": 10.66,
    "volume": 21914400,
    "prev_close": 10.73
  },
  "AAOI": {
    "date": "2026-06-24",
    "open": 149.51,
    "high": 150.34,
    "low": 137.7,
    "close": 146.97,
    "volume": 10456600,
    "prev_close": 147.44
  },
  "MKSI": {
    "date": "2026-06-24",
    "open": 390.54,
    "high": 395.75,
    "low": 376.83,
    "close": 381.62,
    "volume": 1802700,
    "prev_close": 389.17
  },
  "IREN": {
    "date": "2026-06-24",
    "open": 54.09,
    "high": 54.79,
    "low": 48.84,
    "close": 50.3,
    "volume": 38571200,
    "prev_close": 54.72
  },
  "RMBS": {
    "date": "2026-06-24",
    "open": 128.76,
    "high": 131.48,
    "low": 120.01,
    "close": 124.52,
    "volume": 2673800,
    "prev_close": 128.21
  },
  "CAST": {
    "date": "2026-06-24",
    "open": 8.62,
    "high": 9.11,
    "low": 8.05,
    "close": 8.58,
    "volume": 3041800,
    "prev_close": 8.26
  },
  "RAM": {
    "date": "2026-06-24",
    "open": 27.41,
    "high": 33.11,
    "low": 21.81,
    "close": 23.79,
    "volume": 9587195,
    "prev_close": null
  },
  "DLTR": {
    "date": "2026-06-24",
    "open": 115.24,
    "high": 119.39,
    "low": 114.0,
    "close": 119.35,
    "volume": 2586900,
    "prev_close": 113.41
  },
  "TCOM": {
    "date": "2026-06-24",
    "open": 45.34,
    "high": 46.56,
    "low": 45.3,
    "close": 46.3,
    "volume": 2798000,
    "prev_close": 45.5
  },
  "BOXL": {
    "date": "2026-06-24",
    "open": 3.77,
    "high": 8.42,
    "low": 3.64,
    "close": 4.88,
    "volume": 26811300,
    "prev_close": 3.56
  },
  "AXTI": {
    "date": "2026-06-24",
    "open": 77.74,
    "high": 77.98,
    "low": 67.01,
    "close": 70.14,
    "volume": 13837500,
    "prev_close": 77.91
  },
  "BE": {
    "date": "2026-06-24",
    "open": 327.55,
    "high": 345.5,
    "low": 315.01,
    "close": 326.19,
    "volume": 10960300,
    "prev_close": 321.98
  },
  "CGON": {
    "date": "2026-06-24",
    "open": 65.47,
    "high": 71.25,
    "low": 65.03,
    "close": 68.72,
    "volume": 1583700,
    "prev_close": 65.73
  },
  "PASG": {
    "date": "2026-06-24",
    "open": 6.27,
    "high": 6.3,
    "low": 5.78,
    "close": 5.88,
    "volume": 986000,
    "prev_close": 6.12
  },
  "ASML": {
    "date": "2026-06-24",
    "open": 1750.42,
    "high": 1779.65,
    "low": 1730.29,
    "close": 1762.77,
    "volume": 2012900,
    "prev_close": 1778.46
  },
  "WAVE": {
    "date": "2026-06-24",
    "open": 9.0,
    "high": 9.05,
    "low": 8.5,
    "close": 9.02,
    "volume": 17600,
    "prev_close": 8.83
  },
  "QCOM": {
    "date": "2026-06-24",
    "open": 202.57,
    "high": 202.97,
    "low": 191.02,
    "close": 197.41,
    "volume": 25160000,
    "prev_close": 204.13
  },
  "COHR": {
    "date": "2026-06-24",
    "open": 385.1,
    "high": 397.0,
    "low": 365.01,
    "close": 392.5,
    "volume": 4616200,
    "prev_close": 381.22
  },
  "VELO": {
    "date": "2026-06-24",
    "open": 20.37,
    "high": 20.37,
    "low": 17.8,
    "close": 18.05,
    "volume": 3453200,
    "prev_close": 20.66
  },
  "MRVL": {
    "date": "2026-06-24",
    "open": 281.95,
    "high": 281.95,
    "low": 263.66,
    "close": 276.7,
    "volume": 35380200,
    "prev_close": 279.04
  },
  "MRAM": {
    "date": "2026-06-24",
    "open": 22.71,
    "high": 22.78,
    "low": 20.7,
    "close": 21.4,
    "volume": 1606800,
    "prev_close": 22.55
  },
  "ICCM": {
    "date": "2026-06-24",
    "open": 6.03,
    "high": 9.43,
    "low": 6.0,
    "close": 9.3,
    "volume": 13584300,
    "prev_close": 6.12
  },
  "FRMI": {
    "date": "2026-06-24",
    "open": 8.6,
    "high": 9.08,
    "low": 7.91,
    "close": 7.99,
    "volume": 14498500,
    "prev_close": 8.69
  },
  "NVTS": {
    "date": "2026-06-24",
    "open": 21.08,
    "high": 21.13,
    "low": 17.42,
    "close": 18.32,
    "volume": 34106400,
    "prev_close": 21.4
  },
  "LRCX": {
    "date": "2026-06-24",
    "open": 366.87,
    "high": 376.98,
    "low": 361.41,
    "close": 374.8,
    "volume": 11920800,
    "prev_close": 371.33
  },
  "AZI": {
    "date": "2026-06-24",
    "open": 1.18,
    "high": 1.25,
    "low": 1.14,
    "close": 1.14,
    "volume": 12611400,
    "prev_close": 1.18
  },
  "FCUV": {
    "date": "2026-06-24",
    "open": 3.72,
    "high": 4.56,
    "low": 3.35,
    "close": 4.42,
    "volume": 1024100,
    "prev_close": 4.11
  },
  "TREX": {
    "date": "2026-06-24",
    "open": 46.12,
    "high": 49.37,
    "low": 45.2,
    "close": 48.88,
    "volume": 2342300,
    "prev_close": 45.34
  },
  "AVAH": {
    "date": "2026-06-24",
    "open": 8.47,
    "high": 8.63,
    "low": 8.27,
    "close": 8.47,
    "volume": 4296600,
    "prev_close": 8.2
  },
  "NBIS": {
    "date": "2026-06-24",
    "open": 275.1,
    "high": 276.15,
    "low": 249.21,
    "close": 259.66,
    "volume": 15121600,
    "prev_close": 275.25
  },
  "MQ": {
    "date": "2026-06-24",
    "open": 3.82,
    "high": 4.0,
    "low": 3.82,
    "close": 3.97,
    "volume": 4735400,
    "prev_close": 3.83
  },
  "BLDP": {
    "date": "2026-06-24",
    "open": 4.29,
    "high": 4.32,
    "low": 3.64,
    "close": 3.69,
    "volume": 9552100,
    "prev_close": 4.17
  },
  "ALGM": {
    "date": "2026-06-24",
    "open": 55.73,
    "high": 56.79,
    "low": 54.18,
    "close": 55.42,
    "volume": 2611700,
    "prev_close": 55.52
  },
  "WEN": {
    "date": "2026-06-24",
    "open": 7.81,
    "high": 8.89,
    "low": 7.5,
    "close": 7.86,
    "volume": 208544300,
    "prev_close": 6.26
  },
  "AMPX": {
    "date": "2026-06-24",
    "open": 14.3,
    "high": 14.4,
    "low": 12.28,
    "close": 12.52,
    "volume": 12763800,
    "prev_close": 14.12
  },
  "AMAT": {
    "date": "2026-06-24",
    "open": 585.24,
    "high": 594.27,
    "low": 569.49,
    "close": 588.97,
    "volume": 10691500,
    "prev_close": 585.88
  },
  "IXHL": {
    "date": "2026-06-24",
    "open": 3.29,
    "high": 3.34,
    "low": 3.07,
    "close": 3.25,
    "volume": 150200,
    "prev_close": 3.31
  },
  "WYY": {
    "date": "2026-06-24",
    "open": 15.24,
    "high": 18.0,
    "low": 14.75,
    "close": 17.62,
    "volume": 858100,
    "prev_close": 15.27
  },
  "BB": {
    "date": "2026-06-24",
    "open": 8.96,
    "high": 9.38,
    "low": 8.55,
    "close": 8.62,
    "volume": 38187500,
    "prev_close": 8.82
  },
  "MLKN": {
    "date": "2026-06-24",
    "open": 16.29,
    "high": 17.33,
    "low": 16.28,
    "close": 17.24,
    "volume": 1219200,
    "prev_close": 16.06
  },
  "TSHA": {
    "date": "2026-06-24",
    "open": 6.86,
    "high": 7.06,
    "low": 6.83,
    "close": 6.94,
    "volume": 2072200,
    "prev_close": 6.86
  },
  "KLAC": {
    "date": "2026-06-24",
    "open": 242.11,
    "high": 245.3,
    "low": 235.0,
    "close": 240.48,
    "volume": 11510800,
    "prev_close": 244.49
  },
  "STX": {
    "date": "2026-06-24",
    "open": 1027.72,
    "high": 1035.86,
    "low": 953.06,
    "close": 993.25,
    "volume": 4228700,
    "prev_close": 1038.59
  },
  "TECH": {
    "date": "2026-06-24",
    "open": 57.18,
    "high": 60.26,
    "low": 56.85,
    "close": 58.88,
    "volume": 4231400,
    "prev_close": 56.26
  },
  "FND": {
    "date": "2026-06-24",
    "open": 52.6,
    "high": 57.03,
    "low": 52.21,
    "close": 56.94,
    "volume": 3375000,
    "prev_close": 51.46
  },
  "ALAB": {
    "date": "2026-06-24",
    "open": 401.72,
    "high": 421.7,
    "low": 385.12,
    "close": 399.92,
    "volume": 4047700,
    "prev_close": 397.02
  },
  "ASX": {
    "date": "2026-06-24",
    "open": 40.65,
    "high": 42.33,
    "low": 40.3,
    "close": 41.34,
    "volume": 12286200,
    "prev_close": 39.77
  },
  "OUST": {
    "date": "2026-06-24",
    "open": 45.02,
    "high": 45.1,
    "low": 39.0,
    "close": 40.71,
    "volume": 5224800,
    "prev_close": 45.16
  },
  "VRT": {
    "date": "2026-06-24",
    "open": 323.73,
    "high": 323.74,
    "low": 308.28,
    "close": 316.43,
    "volume": 6076300,
    "prev_close": 318.32
  },
  "LABT": {
    "date": "2026-06-24",
    "open": 3.9,
    "high": 4.29,
    "low": 3.46,
    "close": 3.72,
    "volume": 506200,
    "prev_close": 3.97
  },
  "UMC": {
    "date": "2026-06-24",
    "open": 26.4,
    "high": 28.66,
    "low": 26.4,
    "close": 28.01,
    "volume": 24144900,
    "prev_close": 26.2
  },
  "TE": {
    "date": "2026-06-24",
    "open": 9.21,
    "high": 9.21,
    "low": 8.29,
    "close": 8.53,
    "volume": 24320600,
    "prev_close": 9.24
  },
  "MEI": {
    "date": "2026-06-24",
    "open": 13.49,
    "high": 13.74,
    "low": 12.6,
    "close": 13.09,
    "volume": 844800,
    "prev_close": 13.4
  },
  "SNDK": {
    "date": "2026-06-24",
    "open": 1987.53,
    "high": 2021.5,
    "low": 1861.01,
    "close": 1914.46,
    "volume": 10181200,
    "prev_close": 1963.6
  },
  "WOLF": {
    "date": "2026-06-24",
    "open": 48.16,
    "high": 48.56,
    "low": 43.61,
    "close": 45.87,
    "volume": 4649000,
    "prev_close": 48.91
  },
  "FLNC": {
    "date": "2026-06-24",
    "open": 21.44,
    "high": 21.59,
    "low": 19.29,
    "close": 19.75,
    "volume": 8030200,
    "prev_close": 21.21
  },
  "KEEL": {
    "date": "2026-06-24",
    "open": 6.84,
    "high": 6.9,
    "low": 5.85,
    "close": 6.12,
    "volume": 68119200,
    "prev_close": 6.6
  },
  "CRDO": {
    "date": "2026-06-24",
    "open": 281.15,
    "high": 284.0,
    "low": 259.71,
    "close": 268.99,
    "volume": 6621600,
    "prev_close": 272.01
  },
  "INVE": {
    "date": "2026-06-24",
    "open": 3.76,
    "high": 3.76,
    "low": 3.65,
    "close": 3.69,
    "volume": 194200,
    "prev_close": 3.75
  },
  "CRWV": {
    "date": "2026-06-24",
    "open": 103.57,
    "high": 104.54,
    "low": 98.25,
    "close": 100.88,
    "volume": 21943500,
    "prev_close": 105.72
  },
  "ONDS": {
    "date": "2026-06-24",
    "open": 8.48,
    "high": 8.5,
    "low": 7.64,
    "close": 7.68,
    "volume": 73889200,
    "prev_close": 8.53
  },
  "MX": {
    "date": "2026-06-24",
    "open": 5.21,
    "high": 5.26,
    "low": 4.75,
    "close": 4.86,
    "volume": 1433400,
    "prev_close": 5.22
  },
  "ABSI": {
    "date": "2026-06-24",
    "open": 9.51,
    "high": 11.0,
    "low": 8.67,
    "close": 10.07,
    "volume": 38181100,
    "prev_close": 7.41
  },
  "PENG": {
    "date": "2026-06-24",
    "open": 67.0,
    "high": 67.5,
    "low": 61.11,
    "close": 64.72,
    "volume": 2684200,
    "prev_close": 66.96
  },
  "EHGO": {
    "date": "2026-06-24",
    "open": 4.69,
    "high": 6.33,
    "low": 3.37,
    "close": 3.7,
    "volume": 25016200,
    "prev_close": 4.0
  },
  "GLXY": {
    "date": "2026-06-24",
    "open": 31.5,
    "high": 31.68,
    "low": 28.02,
    "close": 28.58,
    "volume": 6726900,
    "prev_close": 31.35
  },
  "SKYQ": {
    "date": "2026-06-24",
    "open": 1.68,
    "high": 2.69,
    "low": 1.64,
    "close": 2.62,
    "volume": 63954200,
    "prev_close": 1.64
  },
  "PURR": {
    "date": "2026-06-24",
    "open": 8.0,
    "high": 8.02,
    "low": 7.72,
    "close": 7.9,
    "volume": 12088700,
    "prev_close": 8.14
  },
  "HTZ": {
    "date": "2026-06-24",
    "open": 3.96,
    "high": 3.98,
    "low": 2.95,
    "close": 3.0,
    "volume": 99546300,
    "prev_close": 5.06
  },
  "INTC": {
    "date": "2026-06-24",
    "open": 133.05,
    "high": 136.08,
    "low": 127.95,
    "close": 131.65,
    "volume": 103472200,
    "prev_close": 132.28
  },
  "WYFI": {
    "date": "2026-06-24",
    "open": 44.72,
    "high": 44.93,
    "low": 36.62,
    "close": 38.71,
    "volume": 4258300,
    "prev_close": 44.76
  },
  "VSH": {
    "date": "2026-06-24",
    "open": 58.51,
    "high": 58.51,
    "low": 53.51,
    "close": 55.59,
    "volume": 6345000,
    "prev_close": 58.96
  },
  "LASE": {
    "date": "2026-06-24",
    "open": 2.09,
    "high": 2.12,
    "low": 1.93,
    "close": 1.94,
    "volume": 2572900,
    "prev_close": 2.16
  },
  "MU": {
    "date": "2026-06-24",
    "open": 1082.22,
    "high": 1083.32,
    "low": 991.1,
    "close": 1048.51,
    "volume": 66708100,
    "prev_close": 1051.77
  },
  "AMKR": {
    "date": "2026-06-24",
    "open": 87.49,
    "high": 87.66,
    "low": 80.22,
    "close": 82.76,
    "volume": 4383800,
    "prev_close": 86.72
  },
  "KUST": {
    "date": "2026-06-24",
    "open": 1.43,
    "high": 1.5,
    "low": 1.39,
    "close": 1.42,
    "volume": 210100,
    "prev_close": 1.41
  },
  "ARM": {
    "date": "2026-06-24",
    "open": 373.33,
    "high": 374.56,
    "low": 344.12,
    "close": 359.08,
    "volume": 8581900,
    "prev_close": 366.39
  },
  "SKM": {
    "date": "2026-06-24",
    "open": 33.09,
    "high": 33.45,
    "low": 32.65,
    "close": 32.96,
    "volume": 2524300,
    "prev_close": 33.45
  },
  "GLW": {
    "date": "2026-06-24",
    "open": 194.42,
    "high": 217.09,
    "low": 190.93,
    "close": 205.83,
    "volume": 19153700,
    "prev_close": 194.07
  },
  "WDC": {
    "date": "2026-06-24",
    "open": 658.46,
    "high": 665.0,
    "low": 612.41,
    "close": 643.83,
    "volume": 12098400,
    "prev_close": 670.75
  },
  "SPRY": {
    "date": "2026-06-24",
    "open": 10.41,
    "high": 10.87,
    "low": 10.38,
    "close": 10.54,
    "volume": 1912800,
    "prev_close": 10.28
  },
  "JHX": {
    "date": "2026-06-24",
    "open": 24.04,
    "high": 26.11,
    "low": 24.04,
    "close": 25.82,
    "volume": 9050700,
    "prev_close": 24.28
  }
}